slides_xp/__init__.py
slides_xp/__main__.py
slides_xp/cli.py
slides_xp/css/root.css
slides_xp/javascript/navigator.js
slides_xp/markdown.py
slides_xp/picker.py
slides_xp/server.py
slides_xp/slide.py
slides_xp/theme_fns.py
slides_xp/themes/__init__.py
slides_xp/themes/default/main.css
slides_xp/themes/default/picker.css
slides_xp/themes/default/slide.css
slides_xp/themes/xp/__init__.py
slides_xp/themes/xp/bliss.jpg
slides_xp/themes/xp/main.css
slides_xp/themes/xp/slide.css
slides_xp/themes/xp/window-bottom-left.png
slides_xp/themes/xp/window-bottom-right.png
slides_xp/themes/xp/window-bottom.png
slides_xp/themes/xp/window-center.png
slides_xp/themes/xp/window-left.png
slides_xp/themes/xp/window-right.png
slides_xp/themes/xp/window-top-left.png
slides_xp/themes/xp/window-top-right.png
slides_xp/themes/xp/window-top.png
slides_xp/themes/xp/window.png
slides_xp/themes/xp/xp.png
slides_xp/util.py
slides_xp-0.0.10.dist-info/WHEEL
slides_xp-0.0.10.dist-info/entry_points.txt
slides_xp-0.0.10.dist-info/METADATA
slides_xp-0.0.10.dist-info/RECORD
