Metadata-Version: 2.3
Name: slides-xp
Version: 0.0.10
Summary: 
Author: Maddy Guthridge
Author-email: Maddy Guthridge <hello@maddyguthridge.com>
Requires-Dist: flask>=3.1.0,<4.0.0
Requires-Dist: pyhtml-enhanced>=2.2.0,<3.0.0
Requires-Dist: click>=8.1.8,<9.0.0
Requires-Dist: mistune>=3.1.1,<4.0.0
Requires-Dist: pygments>=2.19.1,<3.0.0
Requires-Python: >=3.11
